ds_ctcdecoder/__init__.py
ds_ctcdecoder/_swigwrapper.cpython-39-x86_64-linux-gnu.so
ds_ctcdecoder/swigwrapper.py
ds_ctcdecoder-0.9.3.dist-info/COPYING
ds_ctcdecoder-0.9.3.dist-info/LICENSE.paddlepaddle
ds_ctcdecoder-0.9.3.dist-info/LICENSE.parlance
ds_ctcdecoder-0.9.3.dist-info/METADATA
ds_ctcdecoder-0.9.3.dist-info/WHEEL
ds_ctcdecoder-0.9.3.dist-info/top_level.txt
ds_ctcdecoder-0.9.3.dist-info/RECORD
