Metadata-Version: 2.1
Name: ds-ctcdecoder
Version: 0.9.3
Summary: DS CTC decoder
Home-page: UNKNOWN
Author: UNKNOWN
Author-email: UNKNOWN
License: UNKNOWN
Platform: UNKNOWN
Requires-Dist: numpy (>=1.19.4)
